{
  "__credits__": "This vein was automatically generated by OresToFieldGuide.",
  "type": "tfc:disc_vein",
  "config": {
    "height": 10,
    "size": 24,
    "rarity": 130,
    "density": 0.28,
    "min_y": 10,
    "max_y": 70,
    "random_name": "normal_iron",
    "project": false,
    "project_offset": false,
    "near_lava": false,
    "blocks": [
      {
        "replace": [
          "tfc:rock/raw/rhyolite"
        ],
        "with": [
          {
            "block": "tfc:ore/poor_hematite/rhyolite",
            "weight": 20
          },
          {
            "block": "tfc:ore/normal_hematite/rhyolite",
            "weight": 14
          },
          {
            "block": "tfc:ore/rich_hematite/rhyolite",
            "weight": 6
          },
          {
            "block": "tfc:ore/poor_limonite/rhyolite",
            "weight": 36
          },
          {
            "block": "tfc:ore/normal_limonite/rhyolite",
            "weight": 24
          },
          {
            "block": "tfc:ore/rich_limonite/rhyolite",
            "weight": 10
          },
          {
            "block": "gtceu:raw_yellow_limonite_block",
            "weight": 1
          }
        ]
      },
      {
        "replace": [
          "tfc:rock/raw/basalt",
          "minecraft:basalt"
        ],
        "with": [
          {
            "block": "tfc:ore/poor_hematite/basalt",
            "weight": 20
          },
          {
            "block": "tfc:ore/normal_hematite/basalt",
            "weight": 14
          },
          {
            "block": "tfc:ore/rich_hematite/basalt",
            "weight": 6
          },
          {
            "block": "tfc:ore/poor_limonite/basalt",
            "weight": 36
          },
          {
            "block": "tfc:ore/normal_limonite/basalt",
            "weight": 24
          },
          {
            "block": "tfc:ore/rich_limonite/basalt",
            "weight": 10
          },
          {
            "block": "gtceu:raw_yellow_limonite_block",
            "weight": 1
          }
        ]
      },
      {
        "replace": [
          "tfc:rock/raw/andesite"
        ],
        "with": [
          {
            "block": "tfc:ore/poor_hematite/andesite",
            "weight": 20
          },
          {
            "block": "tfc:ore/normal_hematite/andesite",
            "weight": 14
          },
          {
            "block": "tfc:ore/rich_hematite/andesite",
            "weight": 6
          },
          {
            "block": "tfc:ore/poor_limonite/andesite",
            "weight": 36
          },
          {
            "block": "tfc:ore/normal_limonite/andesite",
            "weight": 24
          },
          {
            "block": "tfc:ore/rich_limonite/andesite",
            "weight": 10
          },
          {
            "block": "gtceu:raw_yellow_limonite_block",
            "weight": 1
          }
        ]
      },
      {
        "replace": [
          "tfc:rock/raw/dacite"
        ],
        "with": [
          {
            "block": "tfc:ore/poor_hematite/dacite",
            "weight": 20
          },
          {
            "block": "tfc:ore/normal_hematite/dacite",
            "weight": 14
          },
          {
            "block": "tfc:ore/rich_hematite/dacite",
            "weight": 6
          },
          {
            "block": "tfc:ore/poor_limonite/dacite",
            "weight": 36
          },
          {
            "block": "tfc:ore/normal_limonite/dacite",
            "weight": 24
          },
          {
            "block": "tfc:ore/rich_limonite/dacite",
            "weight": 10
          },
          {
            "block": "gtceu:raw_yellow_limonite_block",
            "weight": 1
          }
        ]
      },
      {
        "replace": [
          "tfc:rock/raw/shale"
        ],
        "with": [
          {
            "block": "tfc:ore/poor_hematite/shale",
            "weight": 20
          },
          {
            "block": "tfc:ore/normal_hematite/shale",
            "weight": 14
          },
          {
            "block": "tfc:ore/rich_hematite/shale",
            "weight": 6
          },
          {
            "block": "tfc:ore/poor_limonite/shale",
            "weight": 36
          },
          {
            "block": "tfc:ore/normal_limonite/shale",
            "weight": 24
          },
          {
            "block": "tfc:ore/rich_limonite/shale",
            "weight": 10
          },
          {
            "block": "gtceu:raw_yellow_limonite_block",
            "weight": 1
          }
        ]
      },
      {
        "replace": [
          "tfc:rock/raw/claystone"
        ],
        "with": [
          {
            "block": "tfc:ore/poor_hematite/claystone",
            "weight": 20
          },
          {
            "block": "tfc:ore/normal_hematite/claystone",
            "weight": 14
          },
          {
            "block": "tfc:ore/rich_hematite/claystone",
            "weight": 6
          },
          {
            "block": "tfc:ore/poor_limonite/claystone",
            "weight": 36
          },
          {
            "block": "tfc:ore/normal_limonite/claystone",
            "weight": 24
          },
          {
            "block": "tfc:ore/rich_limonite/claystone",
            "weight": 10
          },
          {
            "block": "gtceu:raw_yellow_limonite_block",
            "weight": 1
          }
        ]
      },
      {
        "replace": [
          "tfc:rock/raw/limestone"
        ],
        "with": [
          {
            "block": "tfc:ore/poor_hematite/limestone",
            "weight": 20
          },
          {
            "block": "tfc:ore/normal_hematite/limestone",
            "weight": 14
          },
          {
            "block": "tfc:ore/rich_hematite/limestone",
            "weight": 6
          },
          {
            "block": "tfc:ore/poor_limonite/limestone",
            "weight": 36
          },
          {
            "block": "tfc:ore/normal_limonite/limestone",
            "weight": 24
          },
          {
            "block": "tfc:ore/rich_limonite/limestone",
            "weight": 10
          },
          {
            "block": "gtceu:raw_yellow_limonite_block",
            "weight": 1
          }
        ]
      },
      {
        "replace": [
          "tfc:rock/raw/conglomerate"
        ],
        "with": [
          {
            "block": "tfc:ore/poor_hematite/conglomerate",
            "weight": 20
          },
          {
            "block": "tfc:ore/normal_hematite/conglomerate",
            "weight": 14
          },
          {
            "block": "tfc:ore/rich_hematite/conglomerate",
            "weight": 6
          },
          {
            "block": "tfc:ore/poor_limonite/conglomerate",
            "weight": 36
          },
          {
            "block": "tfc:ore/normal_limonite/conglomerate",
            "weight": 24
          },
          {
            "block": "tfc:ore/rich_limonite/conglomerate",
            "weight": 10
          },
          {
            "block": "gtceu:raw_yellow_limonite_block",
            "weight": 1
          }
        ]
      },
      {
        "replace": [
          "tfc:rock/raw/dolomite"
        ],
        "with": [
          {
            "block": "tfc:ore/poor_hematite/dolomite",
            "weight": 20
          },
          {
            "block": "tfc:ore/normal_hematite/dolomite",
            "weight": 14
          },
          {
            "block": "tfc:ore/rich_hematite/dolomite",
            "weight": 6
          },
          {
            "block": "tfc:ore/poor_limonite/dolomite",
            "weight": 36
          },
          {
            "block": "tfc:ore/normal_limonite/dolomite",
            "weight": 24
          },
          {
            "block": "tfc:ore/rich_limonite/dolomite",
            "weight": 10
          },
          {
            "block": "gtceu:raw_yellow_limonite_block",
            "weight": 1
          }
        ]
      },
      {
        "replace": [
          "tfc:rock/raw/chert"
        ],
        "with": [
          {
            "block": "tfc:ore/poor_hematite/chert",
            "weight": 20
          },
          {
            "block": "tfc:ore/normal_hematite/chert",
            "weight": 14
          },
          {
            "block": "tfc:ore/rich_hematite/chert",
            "weight": 6
          },
          {
            "block": "tfc:ore/poor_limonite/chert",
            "weight": 36
          },
          {
            "block": "tfc:ore/normal_limonite/chert",
            "weight": 24
          },
          {
            "block": "tfc:ore/rich_limonite/chert",
            "weight": 10
          },
          {
            "block": "gtceu:raw_yellow_limonite_block",
            "weight": 1
          }
        ]
      },
      {
        "replace": [
          "tfc:rock/raw/chalk"
        ],
        "with": [
          {
            "block": "tfc:ore/poor_hematite/chalk",
            "weight": 20
          },
          {
            "block": "tfc:ore/normal_hematite/chalk",
            "weight": 14
          },
          {
            "block": "tfc:ore/rich_hematite/chalk",
            "weight": 6
          },
          {
            "block": "tfc:ore/poor_limonite/chalk",
            "weight": 36
          },
          {
            "block": "tfc:ore/normal_limonite/chalk",
            "weight": 24
          },
          {
            "block": "tfc:ore/rich_limonite/chalk",
            "weight": 10
          },
          {
            "block": "gtceu:raw_yellow_limonite_block",
            "weight": 1
          }
        ]
      },
      {
        "replace": [
          "minecraft:tuff"
        ],
        "with": [
          {
            "block": "tfc:ore/poor_hematite/tuff",
            "weight": 20
          },
          {
            "block": "tfc:ore/normal_hematite/tuff",
            "weight": 14
          },
          {
            "block": "tfc:ore/rich_hematite/tuff",
            "weight": 6
          },
          {
            "block": "tfc:ore/poor_limonite/tuff",
            "weight": 36
          },
          {
            "block": "tfc:ore/normal_limonite/tuff",
            "weight": 24
          },
          {
            "block": "tfc:ore/rich_limonite/tuff",
            "weight": 10
          },
          {
            "block": "gtceu:raw_yellow_limonite_block",
            "weight": 1
          }
        ]
      }
    ],
    "indicator": {
      "rarity": 19,
      "depth": 70,
      "underground_rarity": 40,
      "underground_count": 200,
      "blocks": [
        {
          "block": "tfc:ore/small_hematite",
          "weight": 40
        },
        {
          "block": "tfc:ore/small_limonite",
          "weight": 70
        }
      ]
    }
  }
}
