{
  "type": "create:sequenced_assembly",
  "ingredient": {
    "item": "minecraft:jungle_slab"
  },
  "results": [
    {
      "id": "railways:track_jungle_narrow"
    }
  ],
  "sequence": [
    {
      "type": "create:cutting",
      "ingredients": [
        {
          "item": "railways:track_incomplete_jungle_narrow"
        }
      ],
      "results": [
        {
          "id": "railways:track_incomplete_jungle_narrow"
        }
      ]
    },
    {
      "type": "create:deploying",
      "ingredients": [
        {
          "item": "railways:track_incomplete_jungle_narrow"
        },
        [
          {
            "item": "gtceu:wrought_iron_screw"
          },
          {
            "tag": "c:nuggets/zinc"
          }
        ]
      ],
      "results": [
        {
          "id": "railways:track_incomplete_jungle_narrow"
        }
      ]
    },
    {
      "type": "create:pressing",
      "ingredients": [
        {
          "item": "railways:track_incomplete_jungle_narrow"
        }
      ],
      "results": [
        {
          "id": "railways:track_incomplete_jungle_narrow"
        }
      ]
    }
  ],
  "transitional_item": {
    "id": "railways:track_incomplete_jungle_narrow"
  }
}